{
  "source_path": "surecharitasi/sites/mysu.sabanciuniv.edu.surecharitasi/files/formlar/fser-c330-02-28.docx",
  "title": "fser-c330-02-28",
  "lang": "tr",
  "html_lang": "",
  "text": "Muayene, Tetkik, Tedavi ve Tıbbi Girişim Red Formu FSER- C330-02-28 Bilincim açık olarak, doktorumdan, tıbbi durumumun ne olduğunu öğrendim ve hastalığımla ilgili olarak hangi muayene, tetkik, tedavi ve girişimlerin uygulanması gerektiği konusunda bilgilendirildim. Oluşabilecek komplikasyonlar (istenmeyen etkiler) ve durumlar, riskler aktarıldı. Önerilen tetkik ve tedavileri kabul etmediğimde sağlığımla ilgili olarak hangi tehlikelere maruz kalabileceğimi öğrendim. Tüm bu bilgilendirmeye rağmen şahsıma herhangi bir muayene, tetkik ve tedavi yapılmasını kendi rızam ile reddediyor ve bu reddin sonucunda ortaya çıkabilecek bütün sorumlulukları üstleniyorum. Hastanın Adı Soyadı: Cep Tel.: İmza : Doktorun Adı Soyadı : İmza : Tarih : Saat : FSER- C330-02-28"
}