{
  "source_path": "surecharitasi/tr/surec/s460-performans-yonetimi.html",
  "title": "S460 Performans Yönetimi | Yönerge",
  "lang": "tr",
  "html_lang": "",
  "text": "Künye Bilgisini Göster İlgili Birimler Süreç Sahibi: Human Resources (İK) Süreç Sorumluları: Süreç Tedarikçileri Süreç Girdisi: İlgili Tedarikçi Çalışanın işe başlaması Süreç Müşterileri Süreç Çıktısı İlgili Müşteri Performans Değerlendirme Notu Çalışan, İlgili Birim / Fakülte Performans Göstergeleri Raporlama Periyodu Zamanı gelip, geçerli bir neden olmaksızın performans değerlendirmesi yapılmamış çalışan oranı Yılda bir Performans notlarının dağılımı Yılda bir Yönerge Prosedür Form İdari Çalışanlar için Performans Sistemi Yönergesi (IHR-S460-02) Öğretim Üyesi Kariyer Gelişim Yolu Seçim Yönergesi (IHR-S460-07) MDBF Başvuru Formu (FHR-S46007-02) SSBF Başvuru Formu (FHR-S46007-03) YBF Başvuru Formu (FHR-S46007-04) devamı... Dil Türkçe"
}